mindspace_web/__init__.py
mindspace_web/templates/_index.html
mindspace_web/templates/_mindspace.js
mindspace_web-1.1.1.dist-info/AUTHORS
mindspace_web-1.1.1.dist-info/LICENSE
mindspace_web-1.1.1.dist-info/METADATA
mindspace_web-1.1.1.dist-info/WHEEL
mindspace_web-1.1.1.dist-info/pbr.json
mindspace_web-1.1.1.dist-info/top_level.txt
mindspace_web-1.1.1.dist-info/RECORD
