Metadata-Version: 2.1
Name: mindspace-web
Version: 1.1.1
Summary: An implementation of mindspace-protocol over websockets
Home-page: https://github.com/chrisnorman7/
Author: Chris Norman
Author-email: chris.norman2@googlemail.com
License: MPL-2
Platform: UNKNOWN
Requires-Dist: attrs
Requires-Dist: twisted
Requires-Dist: autobahn
Requires-Dist: klein
Requires-Dist: jinja2
Requires-Dist: mindspace-protocol
